{
    "idSave": 213,
    "isFirstSession": false,
    "language": "en",
    "promptDone": false,
    "money": 1,
    "newPlayerName": "Hello!",
    "openLevels": [
        false,
        true,
        false
    ],
    "currentWeapon": {
        "instanceID": 31198
    },
    "armor": [
        {
            "instanceID": 32134
        },
        {
            "instanceID": 29382
        },
        {
            "instanceID": 32222
        },
        {
            "instanceID": 32086
        },
        {
            "instanceID": 29556
        },
        {
            "instanceID": 31742
        }
    ],
    "currentEarnPerTime": 0,
    "earnedMoneyCount": 0
}